{
  "artifacts": [
    {
      "timestamp": "2026-03-15T04:30:44.858659+00:00",
      "artifact_type": "generated_rules",
      "artifact_path": "/home/runner/work/111/111/memory/generated_rules.json",
      "metadata": {
        "symbol": "XAUUSD",
        "mode": "replay",
        "rule_count": 0,
        "snapshot_id": "snap_20260315043044855570"
      }
    },
    {
      "timestamp": "2026-03-15T04:30:44.858917+00:00",
      "artifact_type": "meta_adaptive_profile",
      "artifact_path": "/home/runner/work/111/111/memory/meta_adaptive_profile.json",
      "metadata": {
        "symbol": "XAUUSD",
        "mode": "replay",
        "snapshot_id": "snap_20260315043044855570"
      }
    },
    {
      "timestamp": "2026-03-15T04:30:44.867333+00:00",
      "artifact_type": "generated_rules",
      "artifact_path": "/home/runner/work/111/111/memory/generated_rules.json",
      "metadata": {
        "symbol": "XAUUSD",
        "mode": "replay",
        "rule_count": 0,
        "snapshot_id": "snap_20260315043044861553"
      }
    },
    {
      "timestamp": "2026-03-15T04:30:44.867638+00:00",
      "artifact_type": "meta_adaptive_profile",
      "artifact_path": "/home/runner/work/111/111/memory/meta_adaptive_profile.json",
      "metadata": {
        "symbol": "XAUUSD",
        "mode": "replay",
        "snapshot_id": "snap_20260315043044861553"
      }
    },
    {
      "timestamp": "2026-03-15T04:30:44.878579+00:00",
      "artifact_type": "generated_rules",
      "artifact_path": "/home/runner/work/111/111/memory/generated_rules.json",
      "metadata": {
        "symbol": "XAUUSD",
        "mode": "replay",
        "rule_count": 0,
        "snapshot_id": "snap_20260315043044870269"
      }
    },
    {
      "timestamp": "2026-03-15T04:30:44.878851+00:00",
      "artifact_type": "meta_adaptive_profile",
      "artifact_path": "/home/runner/work/111/111/memory/meta_adaptive_profile.json",
      "metadata": {
        "symbol": "XAUUSD",
        "mode": "replay",
        "snapshot_id": "snap_20260315043044870269"
      }
    },
    {
      "timestamp": "2026-03-15T04:30:44.892393+00:00",
      "artifact_type": "generated_rules",
      "artifact_path": "/home/runner/work/111/111/memory/generated_rules.json",
      "metadata": {
        "symbol": "XAUUSD",
        "mode": "replay",
        "rule_count": 0,
        "snapshot_id": "snap_20260315043044881691"
      }
    },
    {
      "timestamp": "2026-03-15T04:30:44.892730+00:00",
      "artifact_type": "meta_adaptive_profile",
      "artifact_path": "/home/runner/work/111/111/memory/meta_adaptive_profile.json",
      "metadata": {
        "symbol": "XAUUSD",
        "mode": "replay",
        "snapshot_id": "snap_20260315043044881691"
      }
    },
    {
      "timestamp": "2026-03-15T05:20:42.222695+00:00",
      "artifact_type": "generated_rules",
      "artifact_path": "/tmp/pytest-of-runner/pytest-0/test_run_pipeline_first_run_li0/memory_live/generated_rules.json",
      "metadata": {
        "symbol": "XAUUSD",
        "mode": "live",
        "rule_count": 0,
        "snapshot_id": "snap_20260315052042218819"
      }
    },
    {
      "timestamp": "2026-03-15T05:20:42.223010+00:00",
      "artifact_type": "meta_adaptive_profile",
      "artifact_path": "memory/meta_adaptive_profile.json",
      "metadata": {
        "symbol": "XAUUSD",
        "mode": "live",
        "snapshot_id": "snap_20260315052042218819"
      }
    },
    {
      "timestamp": "2026-03-15T05:20:42.236174+00:00",
      "artifact_type": "generated_rules",
      "artifact_path": "/tmp/pytest-of-runner/pytest-0/test_run_pipeline_first_run_li0/memory_replay/generated_rules.json",
      "metadata": {
        "symbol": "XAUUSD",
        "mode": "replay",
        "rule_count": 0,
        "snapshot_id": "snap_20260315052042232303"
      }
    },
    {
      "timestamp": "2026-03-15T05:20:42.236521+00:00",
      "artifact_type": "meta_adaptive_profile",
      "artifact_path": "memory/meta_adaptive_profile.json",
      "metadata": {
        "symbol": "XAUUSD",
        "mode": "replay",
        "snapshot_id": "snap_20260315052042232303"
      }
    },
    {
      "timestamp": "2026-03-15T05:20:42.255172+00:00",
      "artifact_type": "generated_rules",
      "artifact_path": "/tmp/pytest-of-runner/pytest-0/test_run_pipeline_compact_outp0/memory/generated_rules.json",
      "metadata": {
        "symbol": "XAUUSD",
        "mode": "replay",
        "rule_count": 0,
        "snapshot_id": "snap_20260315052042249991"
      }
    },
    {
      "timestamp": "2026-03-15T05:20:42.255634+00:00",
      "artifact_type": "meta_adaptive_profile",
      "artifact_path": "memory/meta_adaptive_profile.json",
      "metadata": {
        "symbol": "XAUUSD",
        "mode": "replay",
        "snapshot_id": "snap_20260315052042249991"
      }
    },
    {
      "timestamp": "2026-03-15T05:20:42.271810+00:00",
      "artifact_type": "generated_rules",
      "artifact_path": "/tmp/pytest-of-runner/pytest-0/test_status_panel_exposes_evol0/memory/generated_rules.json",
      "metadata": {
        "symbol": "XAUUSD",
        "mode": "replay",
        "rule_count": 0,
        "snapshot_id": "snap_20260315052042268006"
      }
    },
    {
      "timestamp": "2026-03-15T05:20:42.272174+00:00",
      "artifact_type": "meta_adaptive_profile",
      "artifact_path": "memory/meta_adaptive_profile.json",
      "metadata": {
        "symbol": "XAUUSD",
        "mode": "replay",
        "snapshot_id": "snap_20260315052042268006"
      }
    },
    {
      "timestamp": "2026-03-15T05:20:42.288257+00:00",
      "artifact_type": "generated_rules",
      "artifact_path": "/tmp/pytest-of-runner/pytest-0/test_replay_from_memory_uses_s0/memory/generated_rules.json",
      "metadata": {
        "symbol": "XAUUSD",
        "mode": "live",
        "rule_count": 0,
        "snapshot_id": "snap_20260315052042284475"
      }
    },
    {
      "timestamp": "2026-03-15T05:20:42.288659+00:00",
      "artifact_type": "meta_adaptive_profile",
      "artifact_path": "memory/meta_adaptive_profile.json",
      "metadata": {
        "symbol": "XAUUSD",
        "mode": "live",
        "snapshot_id": "snap_20260315052042284475"
      }
    },
    {
      "timestamp": "2026-03-15T05:20:42.304041+00:00",
      "artifact_type": "generated_rules",
      "artifact_path": "/tmp/pytest-of-runner/pytest-0/test_replay_from_memory_uses_s0/memory/generated_rules.json",
      "metadata": {
        "symbol": "XAUUSD",
        "mode": "replay",
        "rule_count": 0,
        "snapshot_id": "snap_20260315052042296892"
      }
    },
    {
      "timestamp": "2026-03-15T05:20:42.304450+00:00",
      "artifact_type": "meta_adaptive_profile",
      "artifact_path": "memory/meta_adaptive_profile.json",
      "metadata": {
        "symbol": "XAUUSD",
        "mode": "replay",
        "snapshot_id": "snap_20260315052042296892"
      }
    },
    {
      "timestamp": "2026-03-15T06:21:31.412341+00:00",
      "artifact_type": "generated_rules",
      "artifact_path": "/tmp/pytest-of-runner/pytest-6/test_run_pipeline_first_run_li0/memory_live/generated_rules.json",
      "metadata": {
        "symbol": "XAUUSD",
        "mode": "live",
        "rule_count": 0,
        "snapshot_id": "snap_20260315062131408778"
      }
    },
    {
      "timestamp": "2026-03-15T06:21:31.412748+00:00",
      "artifact_type": "meta_adaptive_profile",
      "artifact_path": "memory/meta_adaptive_profile.json",
      "metadata": {
        "symbol": "XAUUSD",
        "mode": "live",
        "snapshot_id": "snap_20260315062131408778"
      }
    },
    {
      "timestamp": "2026-03-15T06:21:31.425748+00:00",
      "artifact_type": "generated_rules",
      "artifact_path": "/tmp/pytest-of-runner/pytest-6/test_run_pipeline_first_run_li0/memory_replay/generated_rules.json",
      "metadata": {
        "symbol": "XAUUSD",
        "mode": "replay",
        "rule_count": 0,
        "snapshot_id": "snap_20260315062131422122"
      }
    },
    {
      "timestamp": "2026-03-15T06:21:31.426163+00:00",
      "artifact_type": "meta_adaptive_profile",
      "artifact_path": "memory/meta_adaptive_profile.json",
      "metadata": {
        "symbol": "XAUUSD",
        "mode": "replay",
        "snapshot_id": "snap_20260315062131422122"
      }
    },
    {
      "timestamp": "2026-03-15T06:21:31.441967+00:00",
      "artifact_type": "generated_rules",
      "artifact_path": "/tmp/pytest-of-runner/pytest-6/test_run_pipeline_compact_outp0/memory/generated_rules.json",
      "metadata": {
        "symbol": "XAUUSD",
        "mode": "replay",
        "rule_count": 0,
        "snapshot_id": "snap_20260315062131438389"
      }
    },
    {
      "timestamp": "2026-03-15T06:21:31.442389+00:00",
      "artifact_type": "meta_adaptive_profile",
      "artifact_path": "memory/meta_adaptive_profile.json",
      "metadata": {
        "symbol": "XAUUSD",
        "mode": "replay",
        "snapshot_id": "snap_20260315062131438389"
      }
    },
    {
      "timestamp": "2026-03-15T06:21:31.458154+00:00",
      "artifact_type": "generated_rules",
      "artifact_path": "/tmp/pytest-of-runner/pytest-6/test_status_panel_exposes_evol0/memory/generated_rules.json",
      "metadata": {
        "symbol": "XAUUSD",
        "mode": "replay",
        "rule_count": 0,
        "snapshot_id": "snap_20260315062131454605"
      }
    },
    {
      "timestamp": "2026-03-15T06:21:31.458690+00:00",
      "artifact_type": "meta_adaptive_profile",
      "artifact_path": "memory/meta_adaptive_profile.json",
      "metadata": {
        "symbol": "XAUUSD",
        "mode": "replay",
        "snapshot_id": "snap_20260315062131454605"
      }
    },
    {
      "timestamp": "2026-03-15T06:21:31.474686+00:00",
      "artifact_type": "generated_rules",
      "artifact_path": "/tmp/pytest-of-runner/pytest-6/test_replay_from_memory_uses_s0/memory/generated_rules.json",
      "metadata": {
        "symbol": "XAUUSD",
        "mode": "live",
        "rule_count": 0,
        "snapshot_id": "snap_20260315062131471012"
      }
    },
    {
      "timestamp": "2026-03-15T06:21:31.475135+00:00",
      "artifact_type": "meta_adaptive_profile",
      "artifact_path": "memory/meta_adaptive_profile.json",
      "metadata": {
        "symbol": "XAUUSD",
        "mode": "live",
        "snapshot_id": "snap_20260315062131471012"
      }
    },
    {
      "timestamp": "2026-03-15T06:21:31.490216+00:00",
      "artifact_type": "generated_rules",
      "artifact_path": "/tmp/pytest-of-runner/pytest-6/test_replay_from_memory_uses_s0/memory/generated_rules.json",
      "metadata": {
        "symbol": "XAUUSD",
        "mode": "replay",
        "rule_count": 0,
        "snapshot_id": "snap_20260315062131483421"
      }
    },
    {
      "timestamp": "2026-03-15T06:21:31.490697+00:00",
      "artifact_type": "meta_adaptive_profile",
      "artifact_path": "memory/meta_adaptive_profile.json",
      "metadata": {
        "symbol": "XAUUSD",
        "mode": "replay",
        "snapshot_id": "snap_20260315062131483421"
      }
    },
    {
      "timestamp": "2026-03-15T06:31:05.254649+00:00",
      "artifact_type": "generated_rules",
      "artifact_path": "/tmp/pytest-of-runner/pytest-0/test_run_pipeline_first_run_li0/memory_live/generated_rules.json",
      "metadata": {
        "symbol": "XAUUSD",
        "mode": "live",
        "rule_count": 0,
        "snapshot_id": "snap_20260315063105250957"
      }
    },
    {
      "timestamp": "2026-03-15T06:31:05.255143+00:00",
      "artifact_type": "meta_adaptive_profile",
      "artifact_path": "memory/meta_adaptive_profile.json",
      "metadata": {
        "symbol": "XAUUSD",
        "mode": "live",
        "snapshot_id": "snap_20260315063105250957"
      }
    },
    {
      "timestamp": "2026-03-15T06:31:05.268859+00:00",
      "artifact_type": "generated_rules",
      "artifact_path": "/tmp/pytest-of-runner/pytest-0/test_run_pipeline_first_run_li0/memory_replay/generated_rules.json",
      "metadata": {
        "symbol": "XAUUSD",
        "mode": "replay",
        "rule_count": 0,
        "snapshot_id": "snap_20260315063105265013"
      }
    },
    {
      "timestamp": "2026-03-15T06:31:05.269401+00:00",
      "artifact_type": "meta_adaptive_profile",
      "artifact_path": "memory/meta_adaptive_profile.json",
      "metadata": {
        "symbol": "XAUUSD",
        "mode": "replay",
        "snapshot_id": "snap_20260315063105265013"
      }
    },
    {
      "timestamp": "2026-03-15T06:31:05.285911+00:00",
      "artifact_type": "generated_rules",
      "artifact_path": "/tmp/pytest-of-runner/pytest-0/test_run_pipeline_compact_outp0/memory/generated_rules.json",
      "metadata": {
        "symbol": "XAUUSD",
        "mode": "replay",
        "rule_count": 0,
        "snapshot_id": "snap_20260315063105282191"
      }
    },
    {
      "timestamp": "2026-03-15T06:31:05.286491+00:00",
      "artifact_type": "meta_adaptive_profile",
      "artifact_path": "memory/meta_adaptive_profile.json",
      "metadata": {
        "symbol": "XAUUSD",
        "mode": "replay",
        "snapshot_id": "snap_20260315063105282191"
      }
    },
    {
      "timestamp": "2026-03-15T06:31:05.302922+00:00",
      "artifact_type": "generated_rules",
      "artifact_path": "/tmp/pytest-of-runner/pytest-0/test_status_panel_exposes_evol0/memory/generated_rules.json",
      "metadata": {
        "symbol": "XAUUSD",
        "mode": "replay",
        "rule_count": 0,
        "snapshot_id": "snap_20260315063105299171"
      }
    },
    {
      "timestamp": "2026-03-15T06:31:05.303541+00:00",
      "artifact_type": "meta_adaptive_profile",
      "artifact_path": "memory/meta_adaptive_profile.json",
      "metadata": {
        "symbol": "XAUUSD",
        "mode": "replay",
        "snapshot_id": "snap_20260315063105299171"
      }
    },
    {
      "timestamp": "2026-03-15T06:31:05.320227+00:00",
      "artifact_type": "generated_rules",
      "artifact_path": "/tmp/pytest-of-runner/pytest-0/test_replay_from_memory_uses_s0/memory/generated_rules.json",
      "metadata": {
        "symbol": "XAUUSD",
        "mode": "live",
        "rule_count": 0,
        "snapshot_id": "snap_20260315063105316488"
      }
    },
    {
      "timestamp": "2026-03-15T06:31:05.320802+00:00",
      "artifact_type": "meta_adaptive_profile",
      "artifact_path": "memory/meta_adaptive_profile.json",
      "metadata": {
        "symbol": "XAUUSD",
        "mode": "live",
        "snapshot_id": "snap_20260315063105316488"
      }
    },
    {
      "timestamp": "2026-03-15T06:31:05.336801+00:00",
      "artifact_type": "generated_rules",
      "artifact_path": "/tmp/pytest-of-runner/pytest-0/test_replay_from_memory_uses_s0/memory/generated_rules.json",
      "metadata": {
        "symbol": "XAUUSD",
        "mode": "replay",
        "rule_count": 0,
        "snapshot_id": "snap_20260315063105329533"
      }
    },
    {
      "timestamp": "2026-03-15T06:31:05.337377+00:00",
      "artifact_type": "meta_adaptive_profile",
      "artifact_path": "memory/meta_adaptive_profile.json",
      "metadata": {
        "symbol": "XAUUSD",
        "mode": "replay",
        "snapshot_id": "snap_20260315063105329533"
      }
    },
    {
      "timestamp": "2026-03-15T06:32:55.635802+00:00",
      "artifact_type": "generated_rules",
      "artifact_path": "/tmp/pytest-of-runner/pytest-2/test_run_pipeline_first_run_li0/memory_live/generated_rules.json",
      "metadata": {
        "symbol": "XAUUSD",
        "mode": "live",
        "rule_count": 0,
        "snapshot_id": "snap_20260315063255631939"
      }
    },
    {
      "timestamp": "2026-03-15T06:32:55.636441+00:00",
      "artifact_type": "meta_adaptive_profile",
      "artifact_path": "memory/meta_adaptive_profile.json",
      "metadata": {
        "symbol": "XAUUSD",
        "mode": "live",
        "snapshot_id": "snap_20260315063255631939"
      }
    },
    {
      "timestamp": "2026-03-15T06:32:55.650480+00:00",
      "artifact_type": "generated_rules",
      "artifact_path": "/tmp/pytest-of-runner/pytest-2/test_run_pipeline_first_run_li0/memory_replay/generated_rules.json",
      "metadata": {
        "symbol": "XAUUSD",
        "mode": "replay",
        "rule_count": 0,
        "snapshot_id": "snap_20260315063255646676"
      }
    },
    {
      "timestamp": "2026-03-15T06:32:55.651119+00:00",
      "artifact_type": "meta_adaptive_profile",
      "artifact_path": "memory/meta_adaptive_profile.json",
      "metadata": {
        "symbol": "XAUUSD",
        "mode": "replay",
        "snapshot_id": "snap_20260315063255646676"
      }
    },
    {
      "timestamp": "2026-03-15T06:32:55.667886+00:00",
      "artifact_type": "generated_rules",
      "artifact_path": "/tmp/pytest-of-runner/pytest-2/test_run_pipeline_compact_outp0/memory/generated_rules.json",
      "metadata": {
        "symbol": "XAUUSD",
        "mode": "replay",
        "rule_count": 0,
        "snapshot_id": "snap_20260315063255664137"
      }
    },
    {
      "timestamp": "2026-03-15T06:32:55.668547+00:00",
      "artifact_type": "meta_adaptive_profile",
      "artifact_path": "memory/meta_adaptive_profile.json",
      "metadata": {
        "symbol": "XAUUSD",
        "mode": "replay",
        "snapshot_id": "snap_20260315063255664137"
      }
    },
    {
      "timestamp": "2026-03-15T06:32:55.685151+00:00",
      "artifact_type": "generated_rules",
      "artifact_path": "/tmp/pytest-of-runner/pytest-2/test_status_panel_exposes_evol0/memory/generated_rules.json",
      "metadata": {
        "symbol": "XAUUSD",
        "mode": "replay",
        "rule_count": 0,
        "snapshot_id": "snap_20260315063255681381"
      }
    },
    {
      "timestamp": "2026-03-15T06:32:55.685844+00:00",
      "artifact_type": "meta_adaptive_profile",
      "artifact_path": "memory/meta_adaptive_profile.json",
      "metadata": {
        "symbol": "XAUUSD",
        "mode": "replay",
        "snapshot_id": "snap_20260315063255681381"
      }
    },
    {
      "timestamp": "2026-03-15T06:32:55.702737+00:00",
      "artifact_type": "generated_rules",
      "artifact_path": "/tmp/pytest-of-runner/pytest-2/test_replay_from_memory_uses_s0/memory/generated_rules.json",
      "metadata": {
        "symbol": "XAUUSD",
        "mode": "live",
        "rule_count": 0,
        "snapshot_id": "snap_20260315063255698934"
      }
    },
    {
      "timestamp": "2026-03-15T06:32:55.703427+00:00",
      "artifact_type": "meta_adaptive_profile",
      "artifact_path": "memory/meta_adaptive_profile.json",
      "metadata": {
        "symbol": "XAUUSD",
        "mode": "live",
        "snapshot_id": "snap_20260315063255698934"
      }
    },
    {
      "timestamp": "2026-03-15T06:32:55.719735+00:00",
      "artifact_type": "generated_rules",
      "artifact_path": "/tmp/pytest-of-runner/pytest-2/test_replay_from_memory_uses_s0/memory/generated_rules.json",
      "metadata": {
        "symbol": "XAUUSD",
        "mode": "replay",
        "rule_count": 0,
        "snapshot_id": "snap_20260315063255712477"
      }
    },
    {
      "timestamp": "2026-03-15T06:32:55.720461+00:00",
      "artifact_type": "meta_adaptive_profile",
      "artifact_path": "memory/meta_adaptive_profile.json",
      "metadata": {
        "symbol": "XAUUSD",
        "mode": "replay",
        "snapshot_id": "snap_20260315063255712477"
      }
    },
    {
      "timestamp": "2026-03-15T06:34:14.342868+00:00",
      "artifact_type": "generated_rules",
      "artifact_path": "/tmp/pytest-of-runner/pytest-4/test_run_pipeline_first_run_li0/memory_live/generated_rules.json",
      "metadata": {
        "symbol": "XAUUSD",
        "mode": "live",
        "rule_count": 0,
        "snapshot_id": "snap_20260315063414338905"
      }
    },
    {
      "timestamp": "2026-03-15T06:34:14.343635+00:00",
      "artifact_type": "meta_adaptive_profile",
      "artifact_path": "memory/meta_adaptive_profile.json",
      "metadata": {
        "symbol": "XAUUSD",
        "mode": "live",
        "snapshot_id": "snap_20260315063414338905"
      }
    },
    {
      "timestamp": "2026-03-15T06:34:14.357632+00:00",
      "artifact_type": "generated_rules",
      "artifact_path": "/tmp/pytest-of-runner/pytest-4/test_run_pipeline_first_run_li0/memory_replay/generated_rules.json",
      "metadata": {
        "symbol": "XAUUSD",
        "mode": "replay",
        "rule_count": 0,
        "snapshot_id": "snap_20260315063414353812"
      }
    },
    {
      "timestamp": "2026-03-15T06:34:14.358386+00:00",
      "artifact_type": "meta_adaptive_profile",
      "artifact_path": "memory/meta_adaptive_profile.json",
      "metadata": {
        "symbol": "XAUUSD",
        "mode": "replay",
        "snapshot_id": "snap_20260315063414353812"
      }
    },
    {
      "timestamp": "2026-03-15T06:34:14.375173+00:00",
      "artifact_type": "generated_rules",
      "artifact_path": "/tmp/pytest-of-runner/pytest-4/test_run_pipeline_compact_outp0/memory/generated_rules.json",
      "metadata": {
        "symbol": "XAUUSD",
        "mode": "replay",
        "rule_count": 0,
        "snapshot_id": "snap_20260315063414371454"
      }
    },
    {
      "timestamp": "2026-03-15T06:34:14.375927+00:00",
      "artifact_type": "meta_adaptive_profile",
      "artifact_path": "memory/meta_adaptive_profile.json",
      "metadata": {
        "symbol": "XAUUSD",
        "mode": "replay",
        "snapshot_id": "snap_20260315063414371454"
      }
    },
    {
      "timestamp": "2026-03-15T06:34:14.392418+00:00",
      "artifact_type": "generated_rules",
      "artifact_path": "/tmp/pytest-of-runner/pytest-4/test_status_panel_exposes_evol0/memory/generated_rules.json",
      "metadata": {
        "symbol": "XAUUSD",
        "mode": "replay",
        "rule_count": 0,
        "snapshot_id": "snap_20260315063414388564"
      }
    },
    {
      "timestamp": "2026-03-15T06:34:14.393169+00:00",
      "artifact_type": "meta_adaptive_profile",
      "artifact_path": "memory/meta_adaptive_profile.json",
      "metadata": {
        "symbol": "XAUUSD",
        "mode": "replay",
        "snapshot_id": "snap_20260315063414388564"
      }
    },
    {
      "timestamp": "2026-03-15T06:34:14.409913+00:00",
      "artifact_type": "generated_rules",
      "artifact_path": "/tmp/pytest-of-runner/pytest-4/test_replay_from_memory_uses_s0/memory/generated_rules.json",
      "metadata": {
        "symbol": "XAUUSD",
        "mode": "live",
        "rule_count": 0,
        "snapshot_id": "snap_20260315063414406071"
      }
    },
    {
      "timestamp": "2026-03-15T06:34:14.410704+00:00",
      "artifact_type": "meta_adaptive_profile",
      "artifact_path": "memory/meta_adaptive_profile.json",
      "metadata": {
        "symbol": "XAUUSD",
        "mode": "live",
        "snapshot_id": "snap_20260315063414406071"
      }
    },
    {
      "timestamp": "2026-03-15T06:34:14.426991+00:00",
      "artifact_type": "generated_rules",
      "artifact_path": "/tmp/pytest-of-runner/pytest-4/test_replay_from_memory_uses_s0/memory/generated_rules.json",
      "metadata": {
        "symbol": "XAUUSD",
        "mode": "replay",
        "rule_count": 0,
        "snapshot_id": "snap_20260315063414419630"
      }
    },
    {
      "timestamp": "2026-03-15T06:34:14.427787+00:00",
      "artifact_type": "meta_adaptive_profile",
      "artifact_path": "memory/meta_adaptive_profile.json",
      "metadata": {
        "symbol": "XAUUSD",
        "mode": "replay",
        "snapshot_id": "snap_20260315063414419630"
      }
    }
  ],
  "schema_version": "v1"
}