{
  "candidate_id": "cand_phase_a_020",
  "module_name": "sandbox_cand_phase_a_020",
  "truth_class": "failure",
  "supervision_source_path": "memory/knowledge_expansion/execution_supervision/cand_phase_a_020.json",
  "portfolio_timestamp": "2026-03-15T10:27:00.892309+00:00",
  "supervision_decision": "blocked_fail_safe",
  "portfolio_decision": "capital_preservation_mode",
  "decision_reason": "Capital preservation activated due to supervision, drawdown, or allocation guardrail breach.",
  "execution_readiness": "not_ready",
  "risk_state": "defensive",
  "allocation_state": "budget_available",
  "exposure_state": "within_limit",
  "sizing_state": "size_constrained",
  "drawdown_state": "within_limit",
  "portfolio_state_snapshot": {
    "timestamp": "2026-03-15T10:27:00.892309+00:00",
    "account_id": "paper",
    "strategy_group": "sandbox",
    "equity": 0.0,
    "peak_equity": 0.0,
    "open_exposure_pct": 0.0,
    "max_exposure_pct": 0.35,
    "suggested_position_size_pct": 0.0,
    "max_position_size_pct": 0.03,
    "capital_budget_pct": 0.25,
    "capital_allocated_pct": 0.0,
    "max_drawdown_pct": 8.0
  },
  "portfolio_state_memory_path": "memory/knowledge_expansion/adaptive_portfolio_state_memory.json",
  "manual_approval_required": true,
  "live_activation_allowed": false,
  "risk_constraints": {
    "live_execution_blocked": true,
    "auto_live_activation": false,
    "paper_execution_only": true,
    "max_exposure_pct": 0.35,
    "max_position_size_pct": 0.03,
    "capital_budget_pct": 0.25,
    "max_drawdown_pct": 8.0,
    "current_exposure_pct": 0.0,
    "current_position_size_pct": 0.0,
    "current_capital_allocated_pct": 0.0,
    "drawdown_pct": 0.0
  },
  "governor_version": "phase_i_governor_v1"
}